{
	"configurations" : 
	[
		{
			"directories" : 
			[
				{
					"build" : ".",
					"hasInstallRule" : true,
					"jsonFile" : "directory-.-1cdf67b4065c3953c58a.json",
					"minimumCMakeVersion" : 
					{
						"string" : "3.20"
					},
					"projectIndex" : 0,
					"source" : ".",
					"targetIndexes" : 
					[
						0,
						1,
						2,
						3,
						4
					]
				}
			],
			"name" : "",
			"projects" : 
			[
				{
					"directoryIndexes" : 
					[
						0
					],
					"name" : "AZ_demo",
					"targetIndexes" : 
					[
						0,
						1,
						2,
						3,
						4
					]
				}
			],
			"targets" : 
			[
				{
					"directoryIndex" : 0,
					"id" : "AZ_demo_uninstall::@6890427a1f51a3e7e1df",
					"jsonFile" : "target-AZ_demo_uninstall-9d4167739d562bdb85db.json",
					"name" : "AZ_demo_uninstall",
					"projectIndex" : 0
				},
				{
					"directoryIndex" : 0,
					"id" : "ament_cmake_python_build_AZ_demo_egg::@6890427a1f51a3e7e1df",
					"jsonFile" : "target-ament_cmake_python_build_AZ_demo_egg-05e9ad47ce437096ed0f.json",
					"name" : "ament_cmake_python_build_AZ_demo_egg",
					"projectIndex" : 0
				},
				{
					"directoryIndex" : 0,
					"id" : "ament_cmake_python_copy_AZ_demo::@6890427a1f51a3e7e1df",
					"jsonFile" : "target-ament_cmake_python_copy_AZ_demo-f7258568b66d52aed791.json",
					"name" : "ament_cmake_python_copy_AZ_demo",
					"projectIndex" : 0
				},
				{
					"directoryIndex" : 0,
					"id" : "ament_cmake_python_copy_AZ_demo_setup::@6890427a1f51a3e7e1df",
					"jsonFile" : "target-ament_cmake_python_copy_AZ_demo_setup-444844793327d49b06df.json",
					"name" : "ament_cmake_python_copy_AZ_demo_setup",
					"projectIndex" : 0
				},
				{
					"directoryIndex" : 0,
					"id" : "uninstall::@6890427a1f51a3e7e1df",
					"jsonFile" : "target-uninstall-ceae086164fee0a83f26.json",
					"name" : "uninstall",
					"projectIndex" : 0
				}
			]
		}
	],
	"kind" : "codemodel",
	"paths" : 
	{
		"build" : "/home/mavis/ros2_ws/src/AZ_demo/build/AZ_demo",
		"source" : "/home/mavis/ros2_ws/src/AZ_demo"
	},
	"version" : 
	{
		"major" : 2,
		"minor" : 6
	}
}
